huaweicloudsdkdcs/__init__.py
huaweicloudsdkdcs/v2/__init__.py
huaweicloudsdkdcs/v2/dcs_async_client.py
huaweicloudsdkdcs/v2/dcs_client.py
huaweicloudsdkdcs/v2/model/__init__.py
huaweicloudsdkdcs/v2/model/acl_account_modify_password_body.py
huaweicloudsdkdcs/v2/model/acl_account_reset_password_body.py
huaweicloudsdkdcs/v2/model/acl_account_resp.py
huaweicloudsdkdcs/v2/model/acl_account_role_modify_body.py
huaweicloudsdkdcs/v2/model/attrs_object.py
huaweicloudsdkdcs/v2/model/autoscan_config_request.py
huaweicloudsdkdcs/v2/model/available_zones.py
huaweicloudsdkdcs/v2/model/backup_files_body.py
huaweicloudsdkdcs/v2/model/backup_instance_body.py
huaweicloudsdkdcs/v2/model/backup_plan.py
huaweicloudsdkdcs/v2/model/backup_policy.py
huaweicloudsdkdcs/v2/model/backup_record_response.py
huaweicloudsdkdcs/v2/model/band_width.py
huaweicloudsdkdcs/v2/model/bandwidth_auto_scaling_policy.py
huaweicloudsdkdcs/v2/model/bandwidth_info.py
huaweicloudsdkdcs/v2/model/batch_create_or_delete_tags_request.py
huaweicloudsdkdcs/v2/model/batch_create_or_delete_tags_response.py
huaweicloudsdkdcs/v2/model/batch_delete_body.py
huaweicloudsdkdcs/v2/model/batch_delete_instances_request.py
huaweicloudsdkdcs/v2/model/batch_delete_instances_response.py
huaweicloudsdkdcs/v2/model/batch_ops_result.py
huaweicloudsdkdcs/v2/model/batch_restart_migration_task_result.py
huaweicloudsdkdcs/v2/model/batch_restart_online_migration_tasks_body.py
huaweicloudsdkdcs/v2/model/batch_restart_online_migration_tasks_request.py
huaweicloudsdkdcs/v2/model/batch_restart_online_migration_tasks_response.py
huaweicloudsdkdcs/v2/model/batch_show_nodes_information_request.py
huaweicloudsdkdcs/v2/model/batch_show_nodes_information_response.py
huaweicloudsdkdcs/v2/model/batch_stop_migration_tasks_body.py
huaweicloudsdkdcs/v2/model/batch_stop_migration_tasks_request.py
huaweicloudsdkdcs/v2/model/batch_stop_migration_tasks_response.py
huaweicloudsdkdcs/v2/model/bigkeys_body.py
huaweicloudsdkdcs/v2/model/bss_param.py
huaweicloudsdkdcs-3.1.184.dist-info/METADATA
huaweicloudsdkdcs-3.1.184.dist-info/WHEEL
huaweicloudsdkdcs-3.1.184.dist-info/licenses/LICENSE
huaweicloudsdkdcs-3.1.184.dist-info/RECORD
